LAB09D/Ejercicio 1/EJ1.v
// Ejercicio 1 Flip Flop tipo D de 1 bit

module FFD1(input clk , input reset, E, input d,  output reg q);

  always@(posedge clk, posedge reset) begin
    if(E == 1) begin
    q <= d;
    end
    if(reset) begin
    q <= 0;
    end
  end
endmodule

// Ejercicio 1 Flip Flop tipo D de 2 bits

module FFD2(input clk , input reset, E, input [1:0]d, output wire [1:0]q);

	FFD1 M1(clk, reset, E, d[0], q[0]);
  FFD1 M2(clk, reset, E, d[1], q[1]);
endmodule

// Ejercicio 1 Flip Flop tipo D de 4 bits

module FFD4(input clk , input reset, E, input [3:0]d, output wire [3:0]q);

	FFD1 G1(clk, reset, E, d[0], q[0]);
  FFD1 G2(clk, reset, E, d[1], q[1]);
  FFD1 G3(clk, reset, E, d[2], q[2]);
  FFD1 G4(clk, reset, E, d[3], q[3]);
endmodule

LAB09D/Ejercicio 1/EJ1_tb.v
module testbench();
	reg clk, reset;
	reg D, E;
  reg [1:0]D1;
  reg [3:0]D2;
	wire Q;
  wire [1:0]Q1;
  wire [3:0]Q2;

	FFD1 P1(clk, reset, E, D, Q);
  FFD2 P2(clk, reset, E, D1, Q1);
  FFD4 P3(clk, reset, E, D2, Q2);

	initial begin
	clk = 0; reset = 0; D=0; D1=2'b00; D2=4'b0000; E=0;
	#1 reset = 1;
  #1 reset = 0;
  #1 D=1; D1=2'b01; D2=4'b0001; E=1;
  #2 D=0; D1=2'b10; D2=4'b0010;
  #1 D=0; D1=2'b11; D2=4'b0011;
  #1 D=1; D1=2'b00; D2=4'b0100;
  #1 D=1; D1=2'b01; D2=4'b0101;
  #1 D=0; D1=2'b10; D2=4'b0110;
  #1 D=1; D1=2'b11; D2=4'b0111;
  #1 D=0; D1=2'b00; D2=4'b1000;
  #1 D=1; D1=2'b01; D2=4'b1001;
  #1 D=0; D1=2'b10; D2=4'b1010;
  #1 D=1; D1=2'b11; D2=4'b1011;
  #1 D=0; D1=2'b00; D2=4'b1100;
  #1 D=1; D1=2'b01; D2=4'b1101;
  #1 D=0; D1=2'b10; D2=4'b1110;
  #1 D=1; D1=2'b11; D2=4'b1111;
	end
	always
    #1 clk = ~clk;
	initial
    #20 $finish;
	initial begin
    $dumpfile("EJ1_tb.vcd");
    $dumpvars(0, testbench);
	end

endmodule

LAB09D/Ejercicio 1/EJ1_tb.vcd
$date
	Sat Oct 31 00:17:33 2020
$end
$version
	Icarus Verilog
$end
$timescale
	1ps
$end
$scope module testbench $end
$var wire 4 ! Q2 [3:0] $end
$var wire 2 " Q1 [1:0] $end
$var wire 1 # Q $end
$var reg 1 $ D $end
$var reg 2 % D1 [1:0] $end
$var reg 4 & D2 [3:0] $end
$var reg 1 ' E $end
$var reg 1 ( clk $end
$var reg 1 ) reset $end
$scope module P1 $end
$var wire 1 ' E $end
$var wire 1 ( clk $end
$var wire 1 $ d $end
$var wire 1 ) reset $end
$var reg 1 # q $end
$upscope $end
$scope module P2 $end
$var wire 1 ' E $end
$var wire 1 ( clk $end
$var wire 2 * d [1:0] $end
$var wire 1 ) reset $end
$var wire 2 + q [1:0] $end
$scope module M1 $end
$var wire 1 ' E $end
$var wire 1 ( clk $end
$var wire 1 , d $end
$var wire 1 ) reset $end
$var reg 1 - q $end
$upscope $end
$scope module M2 $end
$var wire 1 ' E $end
$var wire 1 ( clk $end
$var wire 1 . d $end
$var wire 1 ) reset $end
$var reg 1 / q $end
$upscope $end
$upscope $end
$scope module P3 $end
$var wire 1 ' E $end
$var wire 1 ( clk $end
$var wire 4 0 d [3:0] $end
$var wire 1 ) reset $end
$var wire 4 1 q [3:0] $end
$scope module G1 $end
$var wire 1 ' E $end
$var wire 1 ( clk $end
$var wire 1 2 d $end
$var wire 1 ) reset $end
$var reg 1 3 q $end
$upscope $end
$scope module G2 $end
$var wire 1 ' E $end
$var wire 1 ( clk $end
$var wire 1 4 d $end
$var wire 1 ) reset $end
$var reg 1 5 q $end
$upscope $end
$scope module G3 $end
$var wire 1 ' E $end
$var wire 1 ( clk $end
$var wire 1 6 d $end
$var wire 1 ) reset $end
$var reg 1 7 q $end
$upscope $end
$scope module G4 $end
$var wire 1 ' E $end
$var wire 1 ( clk $end
$var wire 1 8 d $end
$var wire 1 ) reset $end
$var reg 1 9 q $end
$upscope $end
$upscope $end
$upscope $end
$enddefinitions $end
#0
$dumpvars
x9
08
x7
06
x5
04
x3
02
bx 1
b0 0
x/
0.
x-
0,
bx +
b0 *
0)
0(
0'
b0 &
b0 %
0$
x#
bx "
bx !
$end
#1
0#
0-
b0 "
b0 +
0/
03
05
07
b0 !
b0 1
09
1(
1)
#2
0(
0)
#3
b1 !
b1 1
13
b1 "
b1 +
1-
1#
12
1,
1(
1'
b1 &
b1 0
b1 %
b1 *
1$
#4
0(
#5
0#
0-
b10 "
b10 +
1/
03
b10 !
b10 1
15
02
14
0,
1.
1(
b10 &
b10 0
b10 %
b10 *
0$
#6
12
1,
0(
b11 &
b11 0
b11 %
b11 *
#7
17
b100 !
b100 1
05
b0 "
b0 +
0/
1#
02
04
16
0,
0.
1(
b100 &
b100 0
b0 %
b0 *
1$
#8
12
1,
0(
b101 &
b101 0
b1 %
b1 *
#9
0#
b10 "
b10 +
1/
b110 !
b110 1
15
02
14
0,
1.
1(
b110 &
b110 0
b10 %
b10 *
0$
#10
12
1,
0(
b111 &
b111 0
b11 %
b11 *
1$
#11
19
07
b1000 !
b1000 1
05
b0 "
b0 +
0/
02
04
06
18
0,
0.
1(
b1000 &
b1000 0
b0 %
b0 *
0$
#12
12
1,
0(
b1001 &
b1001 0
b1 %
b1 *
1$
#13
b10 "
b10 +
1/
b1010 !
b1010 1
15
02
14
0,
1.
1(
b1010 &
b1010 0
b10 %
b10 *
0$
#14
12
1,
0(
b1011 &
b1011 0
b11 %
b11 *
1$
#15
17
b1100 !
b1100 1
05
b0 "
b0 +
0/
02
04
16
0,
0.
1(
b1100 &
b1100 0
b0 %
b0 *
0$
#16
12
1,
0(
b1101 &
b1101 0
b1 %
b1 *
1$
#17
b10 "
b10 +
1/
b1110 !
b1110 1
15
02
14
0,
1.
1(
b1110 &
b1110 0
b10 %
b10 *
0$
#18
12
1,
0(
b1111 &
b1111 0
b11 %
b11 *
1$
#19
b1111 !
b1111 1
13
b11 "
b11 +
1-
1#
1(
