LAB04D/Ejercicio 5/EJ05.v
// Ejercicio05 SOP Gate Level Modelling Función a implementar: Y = (A * B' * C') + (A * B' * C) + (A * B * C)

module Ej05SOPGLM(input wire A, B, C, output wire Y);

	wire nB, nC, w1, w2, w3;
	not(nB, B);
	not(nC, C);
	and(w1, A, nB, nC);
	and(w2, A, nB, C);
	and(w3, A, B, C);
	or(Y, w1, w2, w3);
endmodule	

// Ejercicio05 SOP Behavior Función a implementar: Y = (A * B' * C') + (A * B' * C) + (A * B * C)

module Ej05SOPB(input wire A, B, C, output wire Y);

	assign Y = (A & ~B & ~C) | (A & ~B & C) | (A & B & C);
endmodule	

// Ejercicio05 POS Gate Level Modelling Función a implementar: Y = (A + B + C) * (A + B + C') * (A + B' + C) * (A + B' + C') * (A' + B' + C)

module Ej05POSGLM(input wire A, B, C, output wire Y);

	wire nA, nB, nC, w1, w2, w3, w4, w5;
	not(nA, A);
	not(nB, B);
	not(nC, C);
	or(w1, A, B, C);
	or(w2, A, B, nC);
	or(w3, A, nB, C);
	or(w4, A, nB, nC);
	or(w5, nA, nB, C);
	and(Y, w1, w2, w3, w4, w5);
endmodule	

// Ejercicio05 POS Behavior Función a implementar: Y = (A + B + C) * (A + B + C') * (A + B' + C) * (A + B' + C') * (A' + B' + C)

module Ej05POSB(input wire A, B, C, output wire Y);

	assign Y = (A | B | C) & (A | B | ~C) & (A | ~B | C) & (A | ~B | ~C) & (~A | ~B | C);
endmodule	

// Ejercicio05 Mapa de Karnaugh Gate Level Modelling Función a implementar: Y = (A * B') + (A * C)

module Ej05MKGLM(input wire A, B, C, output wire Y);

	wire nB, w1, w2, w3;
	not(nB, B);
	and(w1, A, nB);
	and(w2, A, C);
	or(Y, w1, w2);
endmodule	

// Ejercicio05 Mapa de Karnaugh Behavior Función a implementar: Y = (A * B') + (A * C)

module Ej05MKB(input wire A, B, C, output wire Y);

	assign Y = (A & ~B ) | (A & C);
endmodule

LAB04D/Ejercicio 5/EJ05_tb.v
module testbench();
  reg d1, d2, d3, d4, d5, d6, d7, d8, d9, d10, d11, d12, k1, k2, k3, k4, k5, k6;
  wire led1, led2, led3, led4, led5, led6;

  Ej05SOPGLM  G1(d1, d2, d3, led1);
  Ej05SOPB G2(d4, d5, d6, led2);
  Ej05POSGLM  G3(d7, d8, d9, led3);
  Ej05POSB G4(d10, d11, d12, led4);
  Ej05MKGLM G5(k1, k2, k3, led5);
  Ej05MKB  G6(k4, k5, k6, led6);
  
  initial begin
    #1
    $display("\n");
	$display(" Ejercicio 05 SOP GLM ");
    $display("A B C | Y");
    $display("------|--");
    $monitor("%b %b %b | %b", d1, d2, d3, led1);
       d1 = 0; d2 = 0; d3 = 0; 
    #1 d3 = 1;
    #1 d2 = 1; d3 = 0;
    #1 d3 = 1;
    #1 d1 = 1; d2 = 0;d3 = 0;
    #1 d3 = 1;
    #1 d2 = 1; d3 = 0;
    #1 d3 = 1;
	
  end
  
  initial begin
    #9
    $display("\n");
	$display(" Ejercicio 05 SOP B ");
    $display("A B C | Y");
    $display("------|--");
    $monitor("%b %b %b | %b", d4, d5, d6, led2);
       d4 = 0; d5 = 0; d6 = 0; 
    #1 d6 = 1;
    #1 d5 = 1; d6 = 0;
    #1 d6 = 1;
    #1 d4 = 1; d5 = 0;d6 = 0;
    #1 d6 = 1;
    #1 d5 = 1; d6 = 0;
    #1 d6 = 1;
	
  end
  
  
  initial begin
    #27
    $display("\n");
	$display(" Ejercicio 05 POS GLM ");
    $display("A B C | Y");
    $display("------|--");
    $monitor("%b %b %b | %b", d7, d8, d9, led3);
       d7 = 0; d8 = 0; d9 = 0; 
    #1 d9 = 1;
    #1 d8 = 1; d9 = 0;
    #1 d9 = 1;
    #1 d7 = 1; d8 = 0;d9 = 0;
    #1 d9 = 1;
    #1 d8 = 1; d9 = 0;
    #1 d9 = 1;
	
  end
  initial begin
    #40
    $display("\n");
	$display(" Ejercicio 05 POS B ");
    $display("A B C | Y");
    $display("------|--");
    $monitor("%b %b %b | %b", d10, d11, d12, led4);
       d10 = 0; d11 = 0; d12 = 0; 
    #1 d12 = 1;
    #1 d11 = 1; d12 = 0;
    #1 d12 = 1;
    #1 d10 = 1; d11 = 0;d12 = 0;
    #1 d12 = 1;
    #1 d11 = 1; d12 = 0;
    #1 d12 = 1;
	
  end
  
  initial begin
    #55
    $display("\n");
	$display(" Ejercicio 05 Mapa K GLM ");
    $display("A B C | Y");
    $display("------|--");
    $monitor("%b %b %b | %b", k1, k2, k3, led5);
       k1 = 0; k2 = 0; k3 = 0; 
    #1 k3 = 1;
    #1 k2 = 1; k3 = 0;
    #1 k3 = 1;
    #1 k1 = 1; k2 = 0;k3 = 0;
    #1 k3 = 1;
    #1 k2 = 1; k3 = 0;
    #1 k3 = 1;
	
  end
  
  initial begin
    #65
    $display("\n");
	$display(" Ejercicio 05 Mapa K B ");
    $display("A B C | Y");
    $display("------|--");
    $monitor("%b %b %b | %b", k4, k5, k6, led6);
       k4 = 0; k5 = 0; k6 = 0; 
    #1 k6 = 1;
    #1 k5 = 1; k6 = 0;
    #1 k6 = 1;
    #1 k4 = 1; k5 = 0;k6 = 0;
    #1 k6 = 1;
    #1 k5 = 1; k6 = 0;
    #1 k6 = 1;
	
  end
  
 initial
    #85 $finish;
 initial begin
    $dumpfile("EJ05_tb.vcd");
    $dumpvars(0, testbench);
 end
  
endmodule

LAB04D/Ejercicio 5/EJ05_tb.vcd
$date
	Sat Aug 08 18:44:32 2020
$end
$version
	Icarus Verilog
$end
$timescale
	1ps
$end
$scope module testbench $end
$var wire 1 ! led6 $end
$var wire 1 " led5 $end
$var wire 1 # led4 $end
$var wire 1 $ led3 $end
$var wire 1 % led2 $end
$var wire 1 & led1 $end
$var reg 1 ' d1 $end
$var reg 1 ( d10 $end
$var reg 1 ) d11 $end
$var reg 1 * d12 $end
$var reg 1 + d2 $end
$var reg 1 , d3 $end
$var reg 1 - d4 $end
$var reg 1 . d5 $end
$var reg 1 / d6 $end
$var reg 1 0 d7 $end
$var reg 1 1 d8 $end
$var reg 1 2 d9 $end
$var reg 1 3 k1 $end
$var reg 1 4 k2 $end
$var reg 1 5 k3 $end
$var reg 1 6 k4 $end
$var reg 1 7 k5 $end
$var reg 1 8 k6 $end
$scope module G1 $end
$var wire 1 ' A $end
$var wire 1 + B $end
$var wire 1 , C $end
$var wire 1 & Y $end
$var wire 1 9 nB $end
$var wire 1 : nC $end
$var wire 1 ; w1 $end
$var wire 1 < w2 $end
$var wire 1 = w3 $end
$upscope $end
$scope module G2 $end
$var wire 1 - A $end
$var wire 1 . B $end
$var wire 1 / C $end
$var wire 1 % Y $end
$upscope $end
$scope module G3 $end
$var wire 1 0 A $end
$var wire 1 1 B $end
$var wire 1 2 C $end
$var wire 1 $ Y $end
$var wire 1 > nA $end
$var wire 1 ? nB $end
$var wire 1 @ nC $end
$var wire 1 A w1 $end
$var wire 1 B w2 $end
$var wire 1 C w3 $end
$var wire 1 D w4 $end
$var wire 1 E w5 $end
$upscope $end
$scope module G4 $end
$var wire 1 ( A $end
$var wire 1 ) B $end
$var wire 1 * C $end
$var wire 1 # Y $end
$upscope $end
$scope module G5 $end
$var wire 1 3 A $end
$var wire 1 4 B $end
$var wire 1 5 C $end
$var wire 1 " Y $end
$var wire 1 F nB $end
$var wire 1 G w1 $end
$var wire 1 H w2 $end
$upscope $end
$scope module G6 $end
$var wire 1 6 A $end
$var wire 1 7 B $end
$var wire 1 8 C $end
$var wire 1 ! Y $end
$upscope $end
$upscope $end
$enddefinitions $end
#0
$dumpvars
xH
xG
xF
xE
xD
xC
xB
xA
x@
x?
x>
x=
x<
x;
x:
x9
x8
x7
x6
x5
x4
x3
x2
x1
x0
x/
x.
x-
x,
x+
x*
x)
x(
x'
x&
x%
x$
x#
x"
x!
$end
#1
0&
1:
19
0;
0<
0=
0,
0+
0'
#2
0:
1,
#3
1:
09
0,
1+
#4
0:
1,
#5
1&
1;
1:
19
0,
0+
1'
#6
0;
0:
1<
1,
#7
0&
1:
0<
09
0,
1+
#8
1&
0:
1=
1,
#9
0%
0/
0.
0-
#10
1/
#11
0/
1.
#12
1/
#13
1%
0/
0.
1-
#14
1/
#15
0%
0/
1.
#16
1%
1/
#27
0$
1B
1C
1D
1@
1E
1?
1>
0A
02
01
00
#28
0$
0B
0@
1A
12
#29
1@
0C
0?
1B
02
11
#30
0$
0D
0@
1C
12
#31
1$
1@
1?
0>
1D
02
01
10
#32
0@
12
#33
0$
1@
0E
0?
02
11
#34
1$
0@
1E
12
#40
0#
0*
0)
0(
#41
1*
#42
0*
1)
#43
1*
#44
1#
0*
0)
1(
#45
1*
#46
0#
0*
1)
#47
1#
1*
#55
0"
1F
0G
0H
05
04
03
#56
15
#57
0F
05
14
#58
15
#59
1"
1G
1F
05
04
13
#60
1H
15
#61
0"
0G
0H
0F
05
14
#62
1"
1H
15
#65
0!
08
07
06
#66
18
#67
08
17
#68
18
#69
1!
08
07
16
#70
18
#71
0!
08
17
#72
1!
18
