LAB06D/FFD4/FFD4.v
// Ejercicio05 Flip Flop tipo D de 4 bits 

module FFD4A(input clk , input reset, input set, input [3:0]d, output reg[3:0]q);

	always@(posedge clk, posedge reset)
	if(reset)q<=4'b0000;
	else 	q<=d;
	
	always@(posedge clk)
	if(set)q<=4'b1111;
	else 	q<=d;
endmodule

LAB06D/FFD4/FFD4_tb.v
module testbench();
	reg clk, reset, set;
	reg [0:3]D;
	wire [0:3]Q;
	
	FFD4A G1(clk, reset, set, D, Q);
	
	initial begin
	clk = 0;
	reset = 0;
	set = 0;
		
	#1 clk = 0; reset = 1;
	#1 reset = 0;D = 1;D = 0; 
	#1 set = 1; D = 2;
	#1 D = 3;reset = 1; set = 0;
	#1 D = 4;set = 1;
	#1 D = 5;set = 0;
	#1 D = 6; reset = 0;
	#1 D = 7;set = 1;
	#1 D = 8;set = 0;
	#1 D = 9;reset = 1;
	#1 D = 10;set = 1;
	#1 D = 11;reset = 0;
	#1 D = 12;set = 0;
	#1 D = 13;
	#1 D = 14;reset = 1;
	#1 D = 15;reset = 0;
	end
	always
    #2 clk = ~clk; 
	initial
    #200 $finish;
	initial begin
    $dumpfile("FFD4_tb.vcd");
    $dumpvars(0, testbench);
	end
  
endmodule

LAB06D/FFD4/FFD4_tb.vcd
$date
	Sat Sep 05 19:30:42 2020
$end
$version
	Icarus Verilog
$end
$timescale
	1ps
$end
$scope module testbench $end
$var wire 4 ! Q [0:3] $end
$var reg 4 " D [0:3] $end
$var reg 1 # clk $end
$var reg 1 $ reset $end
$var reg 1 % set $end
$scope module G1 $end
$var wire 1 # clk $end
$var wire 4 & d [3:0] $end
$var wire 1 $ reset $end
$var wire 1 % set $end
$var reg 4 ' q [3:0] $end
$upscope $end
$upscope $end
$enddefinitions $end
#0
$dumpvars
bx '
bx &
0%
0$
0#
bx "
bx !
$end
#1
b0 !
b0 '
1$
#2
b0 "
b0 &
0$
1#
#3
b10 "
b10 &
1%
#4
0%
1$
b11 "
b11 &
0#
#5
1%
b100 "
b100 &
#6
b101 !
b101 '
0%
b101 "
b101 &
1#
#7
0$
b110 "
b110 &
#8
1%
b111 "
b111 &
0#
#9
0%
b1000 "
b1000 &
#10
b1001 !
b1001 '
1$
b1001 "
b1001 &
1#
#11
1%
b1010 "
b1010 &
#12
0$
b1011 "
b1011 &
0#
#13
0%
b1100 "
b1100 &
#14
b1101 !
b1101 '
b1101 "
b1101 &
1#
#15
b0 !
b0 '
1$
b1110 "
b1110 &
#16
0$
b1111 "
b1111 &
0#
#18
b1111 !
b1111 '
1#
