LAB09D/Ejercicio 4/EJ4.v
// Ejercicio 4 buffer Tri-estado de 4 bits

module BTE(input E, input [3:0]D,  output [3:0]Q);

    assign Q = E==1?D:4'bzzzz;

endmodule

LAB09D/Ejercicio 4/EJ4_tb.v
module testbench();
  reg E;
  reg [3:0]D;
  wire[3:0]Q;

	BTE P1(E, D, Q);

	initial begin
	E = 0; D=0;
	#1 E = 1;
  #1 D = 4'b0001;
  #1 D = 4'b0010;
  #1 D = 4'b0011;
  #1 D = 4'b0100;
  #1 D = 4'b0101;
  #1 D = 4'b0110;
  #1 D = 4'b0111;E = 0;
  #1 D = 4'b1000;
  #1 D = 4'b1001;
  #1 D = 4'b1010;
  #1 D = 4'b1011;
  #1 D = 4'b1100;
  #1 D = 4'b1101;E = 1;
  #1 D = 4'b1110;
  #1 D = 4'b1111;
	end

	initial
    #20 $finish;
	initial begin
    $dumpfile("EJ4_tb.vcd");
    $dumpvars(0, testbench);
	end

endmodule

LAB09D/Ejercicio 4/EJ4_tb.vcd
$date
	Sat Oct 31 03:42:32 2020
$end
$version
	Icarus Verilog
$end
$timescale
	1ps
$end
$scope module testbench $end
$var wire 4 ! Q [3:0] $end
$var reg 4 " D [3:0] $end
$var reg 1 # E $end
$scope module P1 $end
$var wire 4 $ D [3:0] $end
$var wire 1 # E $end
$var wire 4 % Q [3:0] $end
$upscope $end
$upscope $end
$enddefinitions $end
#0
$dumpvars
bz %
b0 $
0#
b0 "
bz !
$end
#1
b0 !
b0 %
1#
#2
b1 !
b1 %
b1 "
b1 $
#3
b10 !
b10 %
b10 "
b10 $
#4
b11 !
b11 %
b11 "
b11 $
#5
b100 !
b100 %
b100 "
b100 $
#6
b101 !
b101 %
b101 "
b101 $
#7
b110 !
b110 %
b110 "
b110 $
#8
bz !
bz %
0#
b111 "
b111 $
#9
b1000 "
b1000 $
#10
b1001 "
b1001 $
#11
b1010 "
b1010 $
#12
b1011 "
b1011 $
#13
b1100 "
b1100 $
#14
b1101 !
b1101 %
1#
b1101 "
b1101 $
#15
b1110 !
b1110 %
b1110 "
b1110 $
#16
b1111 !
b1111 %
b1111 "
b1111 $
