LAB04D/Ejercicio 4/EJ04.v
// Ejercicio01 Tabla01 Función a implementar: Y = (A' * B' ) + (B' * C')+(A * B') + (A * C)

module Ej01Tabla01(input wire A, B, C, output wire Y);

	
  assign Y = (~A & ~C ) | (~B & ~C) | (A & ~B) | (A & C);
endmodule

// Ejercicio01 Tabla02 Función a implementar: Y = B'

module Ej01Tabla02(input wire A, B, C, output wire Y);

	
  assign Y = (~B);
endmodule

// Ejercicio01 Tabla03 Función a implementar: Y = (A' * B' * C' * D') + (A' * B' * C * D) + (A' * B * C' * D) + (A' * B * C * D') +
//												  (A * B' * C' * D) + (A * B' * C * D') + (A * B * C' * D') + (A * B * C * D)							  

module Ej01Tabla03(input wire A, B, C, D, output wire Y);

	
  assign Y = (~A & ~B & ~C & ~D) | (~A & ~B & C & D) | (~A & B & ~C & D) | (~A & B & C & ~D) | (A & ~B & ~C & D) | (A & ~B & C & ~D) | (A & B & ~C & ~D) | (A & B & C & D);
endmodule

// Ejercicio01 Tabla04 Función a implementar: Y = (B' * D') + (A * B) + (A * C) 							  

module Ej01Tabla04(input wire A, B, C, D, output wire Y);

	
  assign Y = (~B & ~D) | (A & B) | (A & C);
endmodule

// Ejercicio02 Tabla01 Función a implementar: Y = (B' * C' * D') + (A * C') + (A * B') + (A * D')

module Ej02Tabla01(input wire A, B, C, D, output wire Y);

	wire nB, nC, nD, w1, w2, w3, w4;
	not(nB, B);
	not(nC, C);
	not(nD, D);
	and(w1, nB, nC, nD);
	and(w2, A, nC);
	and(w3, A, nB);
	and(w4, A, nD);
	or(Y, w1, w2, w3, w4);
endmodule
	
// Ejercicio02 Tabla02 Función a implementar: Y = C + B'

module Ej02Tabla02(input wire A, B, C, output wire Y);

	wire nB;
	not(nB, B);
	or(Y, nB, C);
endmodule
		
// Ejercicio02 Tabla03 Función a implementar: Y = B +(A * D) + (C' * D)

module Ej02Tabla03(input wire A, B, C, D, output wire Y);

	wire nC, w1, w2, wn2, w3;
	not(nC, C);
	and(w1, A, D);
	and(w2, nC, D);
	or(Y, B, w1, w2);
endmodule
		
// Ejercicio02 Tabla04 Función a implementar: Y = (A' * C') + B

module Ej02Tabla04(input wire A, B, C, output wire Y);

	wire nA, nC, w1;
	not(nA, A);
	not(nC, C);
	and(w1, nA, nC);
	or(Y, w1, B);
endmodule

LAB04D/Ejercicio 4/EJ04_tb.v
module testbench();
  reg p1, p2, p3, p4, p5, p6, p7, p8, p9, p10, p11, p12, p13, p14,
	  b1, b2, b3, b4, b5, b6, b7, b8, b9, b10, b11, b12, b13, b14;
  wire led1, led2, led3, led4, led5, led6, led7, led8;

  Ej01Tabla01  G1(p1, p2, p3, led1);
  Ej01Tabla02  G2(p4, p5, p6, led2);
  Ej01Tabla03  G3(p7, p8, p9, p10, led3);
  Ej01Tabla04  G4(p11, p12, p13, p14, led4);
  Ej02Tabla01  G5(b1, b2, b3, b4, led5);
  Ej02Tabla02  G6(b5, b6, b7, led6);
  Ej02Tabla03  G7(b8, b9, b10, b11, led7);
  Ej02Tabla04  G8(b12, b13, b14, led8);

  
  initial begin
    #1
    $display(" Ejercicio 01 Tabla 01 ");
    $display("A B C | Y ");
    $display("------|----");
    $monitor("%b %b %b | %b ", p1, p2, p3, led1);
       p1 = 0; p2 = 0; p3 = 0;
    #1 p3 = 1;
    #1 p2 = 1; p3 = 0;
    #1 p3 = 1;
    #1 p1 = 1; p2 = 0; p3 = 0;
    #1 p3 = 1;
    #1 p2 = 1; p3 = 0;
    #1 p3 = 1;
  end
  
  initial begin
    #9
    $display("\n");
	$display(" Ejercicio 01 Tabla 02 ");
    $display("A B C | Y");
    $display("------|--");
    $monitor("%b %b %b | %b", p4, p5, p6, led2);
       p4 = 0; p5 = 0; p6 = 0;
    #1 p6 = 1;
    #1 p5 = 1; p6 = 0;
    #1 p6 = 1;
    #1 p4 = 1; p5 = 0; p6 = 0;
    #1 p6 = 1;
    #1 p5 = 1; p6 = 0;
    #1 p6 = 1;
  end
  
 initial begin
    #27
    $display("\n");
	$display(" Ejercicio 01 Tabla 03 ");
    $display("A B C D | Y");
    $display("--------|--");
    $monitor("%b %b %b %b | %b", p7, p8, p9, p10, led3);
       p7 = 0; p8 = 0; p9 = 0; p10 = 0;
    #1 p10 = 1;
    #1 p9 = 1; p10 = 0;
    #1 p10 = 1;
    #1 p8 = 1; p9 = 0; p10 = 0;
    #1 p10 = 1;
    #1 p9 = 1; p10 = 0;
    #1 p10 = 1;
	#1 p7 = 1; p8 = 0; p9 = 0; p10 = 0;
	#1 p10 = 1;
    #1 p9 = 1; p10 = 0;
    #1 p10 = 1;
    #1 p8 = 1; p9 = 0; p10 = 0;
    #1 p10 = 1;
    #1 p9 = 1; p10 = 0;
    #1 p10 = 1;
	
  end
  
  initial begin
    #45
    $display("\n");
	$display(" Ejercicio 01 Tabla 04 ");
    $display("A B C D | Y");
    $display("--------|--");
    $monitor("%b %b %b %b | %b", p11, p12, p13, p14, led4);
       p11 = 0; p12 = 0; p13 = 0; p14 = 0;
    #1 p14 = 1;
    #1 p13 = 1; p14 = 0;
    #1 p14 = 1;
    #1 p12 = 1; p13 = 0; p14 = 0;
    #1 p14 = 1;
    #1 p13 = 1; p14 = 0;
    #1 p14 = 1;
	#1 p11 = 1; p12 = 0; p13 = 0; p14 = 0;
	#1 p14 = 1;
    #1 p13 = 1; p14 = 0;
    #1 p14 = 1;
    #1 p12 = 1; p13 = 0; p14 = 0;
    #1 p14 = 1;
    #1 p13 = 1; p14 = 0;
    #1 p14 = 1;
	
  end
  
  initial begin
    #61
    $display("\n");
	$display(" Ejercicio 02 Tabla 01 ");
    $display("A B C D | Y");
    $display("--------|--");
    $monitor("%b %b %b %b | %b", b1, b2, b3, b4, led5);
       b1 = 0; b2 = 0; b3 = 0; b4 = 0;
    #1 b4 = 1;
    #1 b3 = 1; b4 = 0;
    #1 b4 = 1;
    #1 b2 = 1; b3 = 0; b4 = 0;
    #1 b4 = 1;
    #1 b3 = 1; b4 = 0;
    #1 b4 = 1;
	#1 b1 = 1; b2 = 0; b3 = 0; b4 = 0;
	#1 b4 = 1;
    #1 b3 = 1; b4 = 0;
    #1 b4 = 1;
    #1 b2 = 1; b3 = 0; b4 = 0;
    #1 b4 = 1;
    #1 b3 = 1; b4 = 0;
    #1 b4 = 1;
	
  end
  
    initial begin
    #82
    $display("\n");
	$display(" Ejercicio 02 Tabla 02 ");
    $display("A B C | Y");
    $display("------|--");
    $monitor("%b %b %b | %b", b5, b6, b7, led6);
       b5 = 0; b6 = 0; b7 = 0; 
    #1 b7 = 1;
    #1 b6 = 1; b7 = 0;
    #1 b7 = 1;
    #1 b5 = 1; b6 = 0; b7 = 0;
    #1 b7 = 1;
    #1 b6 = 1; b7 = 0;
    #1 b7 = 1;
	
  end
  
  initial begin
    #96
    $display("\n");
	$display(" Ejercicio 02 Tabla 03 ");
    $display("A B C D | Y");
    $display("--------|--");
    $monitor("%b %b %b %b | %b", b8, b9, b10, b11, led7);
       b8 = 0; b9 = 0; b10 = 0; b11 = 0; 
    #1 b11 = 1;
    #1 b10 = 1; b11 = 0;
    #1 b11 = 1;
    #1 b9 = 1; b10 = 0; b11 = 0;
    #1 b11 = 1;
    #1 b10 = 1; b11 = 0;
    #1 b11 = 1;
	#1 b8 = 1; b9 = 0; b10 = 0; b11 = 0;
    #1 b11 = 1;
    #1 b10 = 1; b11 = 0;
    #1 b11 = 1;
    #1 b9 = 1; b10 = 0; b11 = 0;
    #1 b11 = 1;
	#1 b10 = 1; b11 = 0;
    #1 b11 = 1;
	
  end
  
  initial begin
    #120
    $display("\n");
	$display(" Ejercicio 02 Tabla 04 ");
    $display("A B C | Y");
    $display("------|--");
    $monitor("%b %b %b | %b", b12, b13, b14, led8);
       b12 = 0; b13 = 0; b14 = 0; 
    #1 b14 = 1;
    #1 b13 = 1; b14 = 0;
    #1 b14 = 1;
    #1 b12 = 1; b13 = 0; b14 = 0;
    #1 b14 = 1;
    #1 b13 = 1; b14 = 0;
    #1 b14 = 1;
   end
  
 initial
    #135 $finish;
 initial begin
    $dumpfile("EJ04_tb.vcd");
    $dumpvars(0, testbench);
 end
  
endmodule

LAB04D/Ejercicio 4/EJ04_tb.vcd
$date
	Sat Aug 08 18:19:56 2020
$end
$version
	Icarus Verilog
$end
$timescale
	1ps
$end
$scope module testbench $end
$var wire 1 ! led8 $end
$var wire 1 " led7 $end
$var wire 1 # led6 $end
$var wire 1 $ led5 $end
$var wire 1 % led4 $end
$var wire 1 & led3 $end
$var wire 1 ' led2 $end
$var wire 1 ( led1 $end
$var reg 1 ) b1 $end
$var reg 1 * b10 $end
$var reg 1 + b11 $end
$var reg 1 , b12 $end
$var reg 1 - b13 $end
$var reg 1 . b14 $end
$var reg 1 / b2 $end
$var reg 1 0 b3 $end
$var reg 1 1 b4 $end
$var reg 1 2 b5 $end
$var reg 1 3 b6 $end
$var reg 1 4 b7 $end
$var reg 1 5 b8 $end
$var reg 1 6 b9 $end
$var reg 1 7 p1 $end
$var reg 1 8 p10 $end
$var reg 1 9 p11 $end
$var reg 1 : p12 $end
$var reg 1 ; p13 $end
$var reg 1 < p14 $end
$var reg 1 = p2 $end
$var reg 1 > p3 $end
$var reg 1 ? p4 $end
$var reg 1 @ p5 $end
$var reg 1 A p6 $end
$var reg 1 B p7 $end
$var reg 1 C p8 $end
$var reg 1 D p9 $end
$scope module G1 $end
$var wire 1 7 A $end
$var wire 1 = B $end
$var wire 1 > C $end
$var wire 1 ( Y $end
$upscope $end
$scope module G2 $end
$var wire 1 ? A $end
$var wire 1 @ B $end
$var wire 1 A C $end
$var wire 1 ' Y $end
$upscope $end
$scope module G3 $end
$var wire 1 B A $end
$var wire 1 C B $end
$var wire 1 D C $end
$var wire 1 8 D $end
$var wire 1 & Y $end
$upscope $end
$scope module G4 $end
$var wire 1 9 A $end
$var wire 1 : B $end
$var wire 1 ; C $end
$var wire 1 < D $end
$var wire 1 % Y $end
$upscope $end
$scope module G5 $end
$var wire 1 ) A $end
$var wire 1 / B $end
$var wire 1 0 C $end
$var wire 1 1 D $end
$var wire 1 $ Y $end
$var wire 1 E nB $end
$var wire 1 F nC $end
$var wire 1 G nD $end
$var wire 1 H w1 $end
$var wire 1 I w2 $end
$var wire 1 J w3 $end
$var wire 1 K w4 $end
$upscope $end
$scope module G6 $end
$var wire 1 2 A $end
$var wire 1 3 B $end
$var wire 1 4 C $end
$var wire 1 # Y $end
$var wire 1 L nB $end
$upscope $end
$scope module G7 $end
$var wire 1 5 A $end
$var wire 1 6 B $end
$var wire 1 * C $end
$var wire 1 + D $end
$var wire 1 " Y $end
$var wire 1 M nC $end
$var wire 1 N w1 $end
$var wire 1 O w2 $end
$upscope $end
$scope module G8 $end
$var wire 1 , A $end
$var wire 1 - B $end
$var wire 1 . C $end
$var wire 1 ! Y $end
$var wire 1 P nA $end
$var wire 1 Q nC $end
$var wire 1 R w1 $end
$upscope $end
$upscope $end
$enddefinitions $end
#0
$dumpvars
xR
xQ
xP
xO
xN
xM
xL
xK
xJ
xI
xH
xG
xF
xE
xD
xC
xB
xA
x@
x?
x>
x=
x<
x;
x:
x9
x8
x7
x6
x5
x4
x3
x2
x1
x0
x/
x.
x-
x,
x+
x*
x)
x(
x'
x&
x%
x$
x#
x"
x!
$end
#1
1(
0>
0=
07
#2
0(
1>
#3
1(
0>
1=
#4
0(
1>
#5
1(
0>
0=
17
#6
1>
#7
0(
0>
1=
#8
1(
1>
#9
1'
0A
0@
0?
#10
1A
#11
0'
0A
1@
#12
1A
#13
1'
0A
0@
1?
#14
1A
#15
0'
0A
1@
#16
1A
#27
1&
08
0D
0C
0B
#28
0&
18
#29
08
1D
#30
1&
18
#31
0&
08
0D
1C
#32
1&
18
#33
08
1D
#34
0&
18
#35
08
0D
0C
1B
#36
1&
18
#37
08
1D
#38
0&
18
#39
1&
08
0D
1C
#40
0&
18
#41
08
1D
#42
1&
18
#45
1%
0<
0;
0:
09
#46
0%
1<
#47
1%
0<
1;
#48
0%
1<
#49
0<
0;
1:
#50
1<
#51
0<
1;
#52
1<
#53
1%
0<
0;
0:
19
#54
0%
1<
#55
1%
0<
1;
#56
1<
#57
0<
0;
1:
#58
1<
#59
0<
1;
#60
1<
#61
1$
1H
1G
1F
1E
0I
0J
0K
01
00
0/
0)
#62
0$
0H
0G
11
#63
1G
0F
01
10
#64
0G
11
#65
1G
1F
0E
01
00
1/
#66
0G
11
#67
1G
0F
01
10
#68
0G
11
#69
1$
1K
1I
1H
1J
1G
1F
1E
01
00
0/
1)
#70
0H
0K
0G
11
#71
1K
0I
1G
0F
01
10
#72
0K
0G
11
#73
1K
1I
0J
1G
1F
0E
01
00
1/
#74
0K
0G
11
#75
1K
0I
1G
0F
01
10
#76
0$
0K
0G
11
#82
1#
1L
04
03
02
#83
14
#84
0#
0L
04
13
#85
1#
14
#86
1L
04
03
12
#87
14
#88
0#
0L
04
13
#89
1#
14
#96
0"
0O
1M
0N
0+
0*
06
05
#97
1"
1O
1+
#98
0"
0O
0M
0+
1*
#99
1+
#100
1M
1"
0+
0*
16
#101
1O
1+
#102
0O
0M
0+
1*
#103
1+
#104
1M
0"
0+
0*
06
15
#105
1"
1N
1O
1+
#106
0"
0N
0O
0M
0+
1*
#107
1"
1N
1+
#108
0N
1M
0+
0*
16
#109
1N
1O
1+
#110
0N
0O
0M
0+
1*
#111
1N
1+
#120
1!
1R
1Q
1P
0.
0-
0,
#121
0!
0R
0Q
1.
#122
1R
1Q
1!
0.
1-
#123
0R
0Q
1.
#124
1Q
0!
0P
0.
0-
1,
#125
0Q
1.
#126
1Q
1!
0.
1-
#127
0Q
1.
