LAB09D/Ejercicio 3/EJ03.v
// Ejercicio 3 Flip Flop tipo D de 1 bit

module FFD1(input clk , input reset, E, input d,  output reg q);

  always@(posedge clk, posedge reset) begin
    if(E == 1) begin
    q <= d;
    end
    if(reset) begin
    q <= 0;
    end
  end
endmodule

// Ejercicio 3 Flip Flop JK de 1 bit

module FFJK(input clk , input reset, E, J, K, output Q);
  wire nK, nQ, w1, w2, D;
  not(nK, K);
  not(nQ, Q);
  and(w1, nK, Q);
  and(w2, nQ, J);
  or (D, w1, w2);

  FFD1 M1(clk, reset, E, D, Q);
endmodule

LAB09D/Ejercicio 3/EJ03_tb.v
module testbench();
	reg clk, reset;
	reg J, K, E;
	wire Q;

	FFJK P1(clk, reset, E, J, K, Q);

	initial begin
	clk = 0; reset = 0; J = 0; K = 0; E = 0;
	#1 reset = 1; E=1;
  #1 reset = 0;
  #2 J=0; K=0;
  #2 J=1; K=0;
  #2 J=0; K=0;
  #2 J=0; K=1;
  #2 J=0; K=0;
  #2 J=1; K=1;

	end
	always
    #1 clk = ~clk;
	initial
    #20 $finish;
	initial begin
    $dumpfile("EJ03_tb.vcd");
    $dumpvars(0, testbench);
	end

endmodule

LAB09D/Ejercicio 3/EJ03_tb.vcd
$date
	Sat Oct 31 01:10:24 2020
$end
$version
	Icarus Verilog
$end
$timescale
	1ps
$end
$scope module testbench $end
$var wire 1 ! Q $end
$var reg 1 " E $end
$var reg 1 # J $end
$var reg 1 $ K $end
$var reg 1 % clk $end
$var reg 1 & reset $end
$scope module P1 $end
$var wire 1 ' D $end
$var wire 1 " E $end
$var wire 1 # J $end
$var wire 1 $ K $end
$var wire 1 % clk $end
$var wire 1 ( nK $end
$var wire 1 ) nQ $end
$var wire 1 & reset $end
$var wire 1 * w1 $end
$var wire 1 + w2 $end
$var wire 1 ! Q $end
$scope module M1 $end
$var wire 1 " E $end
$var wire 1 % clk $end
$var wire 1 ' d $end
$var wire 1 & reset $end
$var reg 1 ! q $end
$upscope $end
$upscope $end
$upscope $end
$enddefinitions $end
#0
$dumpvars
0+
x*
x)
1(
x'
0&
0%
0$
0#
0"
x!
$end
#1
0'
0*
1)
0!
1%
1"
1&
#2
0%
0&
#3
1%
#4
0%
#5
1%
#6
1'
1+
0%
1#
#7
0+
1*
0)
1!
1%
#8
0%
0#
#9
1%
#10
0'
0*
0(
0%
1$
#11
1)
0!
1%
#12
1(
0%
0$
#13
1%
#14
1'
0(
1+
0%
1$
1#
#15
0'
0+
0)
1!
1%
#16
0%
#17
1'
1+
1)
0!
1%
#18
0%
#19
0'
0+
0)
1!
1%
