LAB09D/Ejercicio 5/EJ5.v
module ROM(input wire [6:0]IN, output logic [12:0]OTP);

reg[12:0] DATA;

	always @(*) begin
		casez (IN)
			7'b??????0: DATA = 13'b1000000001000;
			7'b00001?1: DATA = 13'b0100000001000;
			7'b00000?1: DATA = 13'b1000000001000;
			7'b00011?1: DATA = 13'b1000000001000;
			7'b00010?1: DATA = 13'b0100000001000;
			7'b0010??1: DATA = 13'b0001001000010;
			7'b0011??1: DATA = 13'b1001001100000;
			7'b0100??1: DATA = 13'b0011010000010;
			7'b0101??1: DATA = 13'b0011010000100;
			7'b0110??1: DATA = 13'b1011010100000;
			7'b0111??1: DATA = 13'b1000000111000;
			7'b1000?11: DATA = 13'b0100000001000;
			7'b1000?01: DATA = 13'b1000000001000;
			7'b1001?11: DATA = 13'b1000000001000;
			7'b1001?01: DATA = 13'b0100000001000;
			7'b1010??1: DATA = 13'b0011011000010;
			7'b1011??1: DATA = 13'b1011011100000;
			7'b1100??1: DATA = 13'b0100000001000;
			7'b1101??1: DATA = 13'b0000000001001;
			7'b1110??1: DATA = 13'b0011100000010;
			7'b1111??1: DATA = 13'b1011100100000;
			default: DATA = 13'bxxxxxxxxxxxxx;
		endcase
		assign OTP = DATA;
end
endmodule

LAB09D/Ejercicio 5/EJ5_tb.v
module testbench();
  reg [6:0]IN;
  wire[12:0]OTP;

	ROM P1(IN, OTP);

	initial begin
	IN = 0;
	#1 IN = 7'b0000000;
  #1 IN = 7'b0000101;
  #1 IN = 7'b0000001;
  #1 IN = 7'b0001101;
  #1 IN = 7'b0001001;
  #1 IN = 7'b0010001;
  #1 IN = 7'b0011001;
  #1 IN = 7'b0100001;
  #1 IN = 7'b0101001;
  #1 IN = 7'b0110001;
  #1 IN = 7'b0111001;
  #1 IN = 7'b1000011;
  #1 IN = 7'b1000001;
  #1 IN = 7'b1001011;
  #1 IN = 7'b1001001;
  #1 IN = 7'b1010001;
  #1 IN = 7'b1011001;
  #1 IN = 7'b1100001;
  #1 IN = 7'b1101001;
  #1 IN = 7'b1110001;
  #1 IN = 7'b1111001;
  #1 IN = 7'b0000111;
  #1 IN = 7'b0000011;
  #1 IN = 7'b0001111;
  #1 IN = 7'b0001011;
  #1 IN = 7'b0010111;
	end

	initial
    #30 $finish;
	initial begin
    $dumpfile("EJ5_tb.vcd");
    $dumpvars(0, testbench);
	end
endmodule

LAB09D/Ejercicio 5/EJ5_tb.vcd
$date
	Sat Oct 31 02:19:13 2020
$end
$version
	Icarus Verilog
$end
$timescale
	1ps
$end
$scope module testbench $end
$var wire 13 ! OTP [12:0] $end
$var reg 7 " IN [6:0] $end
$scope module P1 $end
$var wire 7 # IN [6:0] $end
$var reg 13 $ DATA [12:0] $end
$var reg 13 % OTP [12:0] $end
$upscope $end
$upscope $end
$enddefinitions $end
#0
$dumpvars
b1000000001000 %
b1000000001000 $
b0 #
b0 "
b1000000001000 !
$end
#2
b100000001000 !
b100000001000 %
b100000001000 $
b101 "
b101 #
#3
b1000000001000 !
b1000000001000 %
b1000000001000 $
b1 "
b1 #
#4
b1101 "
b1101 #
#5
b100000001000 !
b100000001000 %
b100000001000 $
b1001 "
b1001 #
#6
b1001000010 !
b1001000010 %
b1001000010 $
b10001 "
b10001 #
#7
b1001001100000 !
b1001001100000 %
b1001001100000 $
b11001 "
b11001 #
#8
b11010000010 !
b11010000010 %
b11010000010 $
b100001 "
b100001 #
#9
b11010000100 !
b11010000100 %
b11010000100 $
b101001 "
b101001 #
#10
b1011010100000 !
b1011010100000 %
b1011010100000 $
b110001 "
b110001 #
#11
b1000000111000 !
b1000000111000 %
b1000000111000 $
b111001 "
b111001 #
#12
b100000001000 !
b100000001000 %
b100000001000 $
b1000011 "
b1000011 #
#13
b1000000001000 !
b1000000001000 %
b1000000001000 $
b1000001 "
b1000001 #
#14
b1001011 "
b1001011 #
#15
b100000001000 !
b100000001000 %
b100000001000 $
b1001001 "
b1001001 #
#16
b11011000010 !
b11011000010 %
b11011000010 $
b1010001 "
b1010001 #
#17
b1011011100000 !
b1011011100000 %
b1011011100000 $
b1011001 "
b1011001 #
#18
b100000001000 !
b100000001000 %
b100000001000 $
b1100001 "
b1100001 #
#19
b1001 !
b1001 %
b1001 $
b1101001 "
b1101001 #
#20
b11100000010 !
b11100000010 %
b11100000010 $
b1110001 "
b1110001 #
#21
b1011100100000 !
b1011100100000 %
b1011100100000 $
b1111001 "
b1111001 #
#22
b100000001000 !
b100000001000 %
b100000001000 $
b111 "
b111 #
#23
b1000000001000 !
b1000000001000 %
b1000000001000 $
b11 "
b11 #
#24
b1111 "
b1111 #
#25
b100000001000 !
b100000001000 %
b100000001000 $
b1011 "
b1011 #
#26
b1001000010 !
b1001000010 %
b1001000010 $
b10111 "
b10111 #
