LAB06D/EJ0603/EJ0603.v
//Flip Flop
module FF (input clk, reset, D, output reg Q);
    always @ (posedge clk or posedge reset)begin
    if (reset)
		Q <= 1'b0;
    else
		Q <= D;
    end
endmodule

//Ejercicio 03
module EJ03(input A, clk, reset, output wire Y1, Y2, Y3);
    wire S0, S1, S2, S00, S11, S22;

    assign S00 = (~S1 & ~S0 & ~A) | (S1 & ~S0 & A) | (S2 & S0);
    assign S01 = (~S2 & S0 & A) | (S2 & S0 & ~A) | (S1 & ~S0);
    assign S22 = (~S2 & ~S1 & A) | (S2 & ~S1 & ~A) | (~S2 & S1 & ~A) | (S2 & S1 & A);

    FF U1(clk, reset, S00, S0);
    FF U2(clk, reset, S11, S1);
    FF U3(clk, reset, S22, S2);

    assign Y1 = S0;
    assign Y2 = S1;
    assign Y3 = S2;

endmodule

LAB06D/EJ0603/EJ0603_tb.v
module testbench();
	reg clk, reset, A;
	wire Y1, Y2, Y3;
	EJ03 D1(A, clk, reset, Y1, Y2, Y3);
	
	initial begin
    $display("\n");
	$display(" Ejercicio 01");
    $display("clk reset A B SF SP | Y");
    $display("--------------------|--");
    $monitor("%b %b %b %b %b %b | %b", clk, reset, A, Y1, Y2, Y3);
	end
	
	initial begin
	clk = 0;
	reset = 0;
	A = 0;
	#1 reset = 1;
	#1 reset = 0;
	#10
	A = 1;
	#20
	A = 0;
	#30
	A = 1;
	#40
	A = 0;
	#50
	A = 1;
	#60
	A = 0;
	#70
	A = 1;
	end
	always
    #5 clk = ~clk; 
	initial
    #150 $finish;
	initial begin
    $dumpfile("EJ0603_tb.vcd");
    $dumpvars(0, testbench);
	end
  
endmodule

LAB06D/EJ0603/EJ0603_tb.vcd
$date
	Sat Sep 05 23:41:31 2020
$end
$version
	Icarus Verilog
$end
$timescale
	1ps
$end
$scope module testbench $end
$var wire 1 ! Y3 $end
$var wire 1 " Y2 $end
$var wire 1 # Y1 $end
$var reg 1 $ A $end
$var reg 1 % clk $end
$var reg 1 & reset $end
$scope module D1 $end
$var wire 1 $ A $end
$var wire 1 ' S00 $end
$var wire 1 ( S01 $end
$var wire 1 ) S11 $end
$var wire 1 * S22 $end
$var wire 1 # Y1 $end
$var wire 1 " Y2 $end
$var wire 1 ! Y3 $end
$var wire 1 % clk $end
$var wire 1 & reset $end
$var wire 1 + S2 $end
$var wire 1 , S1 $end
$var wire 1 - S0 $end
$scope module U1 $end
$var wire 1 ' D $end
$var wire 1 % clk $end
$var wire 1 & reset $end
$var reg 1 - Q $end
$upscope $end
$scope module U2 $end
$var wire 1 ) D $end
$var wire 1 % clk $end
$var wire 1 & reset $end
$var reg 1 , Q $end
$upscope $end
$scope module U3 $end
$var wire 1 * D $end
$var wire 1 % clk $end
$var wire 1 & reset $end
$var reg 1 + Q $end
$upscope $end
$upscope $end
$upscope $end
$enddefinitions $end
#0
$dumpvars
x-
x,
x+
x*
z)
x(
x'
0&
0%
0$
x#
x"
x!
$end
#1
1'
0*
0(
0#
0-
0"
0,
0!
0+
1&
#2
0&
#5
0'
x*
z"
z,
1#
1-
1%
#10
0%
#12
1(
1$
#15
x'
x(
0#
0-
x!
x+
1%
#20
0%
#25
x#
x-
1%
#30
0%
#32
0$
#35
1%
#40
0%
#45
1%
#50
0%
#55
1%
#60
0%
#62
1$
#65
1%
#70
0%
#75
1%
#80
0%
#85
1%
#90
0%
#95
1%
#100
0%
#102
0$
