LAB08D/Ejercicio2/EJ2.v
module ROM(input wire [11:0]address, output wire[7:0]val);
reg[7:0] M[0:4095];
initial begin
    $readmemh("ROMM.list",M);
    end
    assign val = M[address];
    endmodule

LAB08D/Ejercicio2/EJ2_tb.v
module testbench();

reg [11:0]address;
wire [7:0]val;

ROM U1(address, val);

initial begin
$display("Memoria ROM");
$display("    Address     |  Data");
$display("------------|---------");
$monitor("%b | %b", address, val);

address=12'b0;
#1 address=12'b000000000001;
#1 address=12'b000000000010;
#1 address=12'b000000000011;
#1 address=12'b000000000100;
#1 address=12'b000000000101;
#1 address=12'b000000000110;
#1 address=12'b000000000111;
#1 address=12'b000000001000;
#1 address=12'b000000001001;
#1 address=12'b000000001010;
#1 address=12'b000000001011;
end
initial
#13 $finish;

initial begin

    $dumpfile("EJ2_tb.vcd");
    $dumpvars(0,testbench);
  end
endmodule

LAB08D/Ejercicio2/EJ2_tb.vcd
$date
	Sat Oct 24 18:41:46 2020
$end
$version
	Icarus Verilog
$end
$timescale
	1ps
$end
$scope module testbench $end
$var wire 8 ! val [7:0] $end
$var reg 12 " address [11:0] $end
$scope module U1 $end
$var wire 12 # address [11:0] $end
$var wire 8 $ val [7:0] $end
$upscope $end
$upscope $end
$enddefinitions $end
#0
$dumpvars
b1 $
b0 #
b0 "
b1 !
$end
#1
b101 !
b101 $
b1 "
b1 #
#2
b1000 !
b1000 $
b10 "
b10 #
#3
b10 !
b10 $
b11 "
b11 #
#4
b1001 !
b1001 $
b100 "
b100 #
#5
b10000 !
b10000 $
b101 "
b101 #
#6
bx !
bx $
b110 "
b110 #
#7
b111 "
b111 #
#8
b1000 "
b1000 #
#9
b111 !
b111 $
b1001 "
b1001 #
#10
b110 !
b110 $
b1010 "
b1010 #
#11
b100 !
b100 $
b1011 "
b1011 #
