LAB10D/Ejercicio 2/EJ02.v
// Buffer Tri-estado de 4 bits
module BTE(input E, input [3:0]D,  output [3:0]Q);

    assign Q = E==1?D:4'bzzzz;

endmodule

//Flip Flop tipo D de 1 bit

module FFD1(input clk , input reset, E, input d,  output reg q);

  always@(posedge clk, posedge reset) begin
    if(E == 1) begin
    q <= d;
    end
    if(reset) begin
    q <= 0;
    end
  end
endmodule

//Flip Flop tipo D de 4 bits

module FFD4(input clk , input reset, E, input [3:0]d, output wire [3:0]q);

	FFD1 G1(clk, reset, E, d[0], q[0]);
  FFD1 G2(clk, reset, E, d[1], q[1]);
  FFD1 G3(clk, reset, E, d[2], q[2]);
  FFD1 G4(clk, reset, E, d[3], q[3]);
endmodule

//Modulo de la ALU

module ALU (input [2:0]F,input [3:0]A, B, output reg[3:0]salida, output reg carry, zero);
reg [4:0]CS,CR;
always @(F,A,B) begin
    case(F)
    3'b000: begin
    salida = A;
    carry = 0;
    end
    3'b001: begin
    CR = A-B;
    carry = CR[4];
    salida = A;
    end
    3'b010: begin
    salida = B;
    carry = 0;
    end
    3'b011: begin
    CS = A + B;
    carry = CS[4];
    salida = CS[3:0];
    end
    3'b100: begin
    salida = ~(A & B);
    carry = 0;
    end
    default: salida = A;
  endcase
  end
  always@(salida) begin
  if(salida == 0) begin
  zero = 1;
  end
  else
  zero = 0;
  end

endmodule

//Modulo de conexiones

module EJ02(input clk, reset, enable1, enable2, enable3, input [3:0]entrada, input [2:0]S, output Carry, Zero, output [3:0]salida);

  wire [3:0]data_bus, accu;
  wire [3:0]aluc;

  BTE U1(enable1, entrada,data_bus);
  FFD4 U2(clk, reset, enable2, aluc, accu);
  ALU U3(S, accu, data_bus, aluc, Carry, Zero);
  assign salida = aluc;
endmodule

LAB10D/Ejercicio 2/EJ02 - copia.v
module testbench();
reg clck, rst, EN1, EN2, EN3;
reg [3:0]Entrada;
reg [2:0]S;
wire Carry, Zero;
wire [3:0]salida;
EJ02 M1(clck, rst, EN1, EN2, EN3, Entrada, S, Carry, Zero, salida);

initial begin
clck=0; rst=0; EN1=0; EN2=0; EN3=0; Entrada=0; S=0;
#1 rst=1;
#1 rst=0;
#1 Entrada= 4'b0010; EN1=1; EN2=1; EN3=1;S=3'b000;
#4 Entrada= 4'b0001; S=3'b010;
#4 Entrada= 4'b0011;
#4 Entrada= 4'b0100; S=3'b011;
#4 Entrada= 4'b0101; S=3'b100;
#4 Entrada= 4'b1010; S=3'b001;
#2 Entrada= 4'b0111;
#4 Entrada= 4'b0111; S=3'b011;

end
always
#1 clck = ~clck;
initial
#40 $finish;

initial begin

    $dumpfile("EJ02_tb.vcd");
    $dumpvars(0,testbench);
  end
endmodule

LAB10D/Ejercicio 2/EJ02_tb.vcd
$date
	Sat Nov 07 23:41:16 2020
$end
$version
	Icarus Verilog
$end
$timescale
	1ps
$end
$scope module testbench $end
$var wire 4 ! salida [3:0] $end
$var wire 1 " Zero $end
$var wire 1 # Carry $end
$var reg 1 $ EN1 $end
$var reg 1 % EN2 $end
$var reg 1 & EN3 $end
$var reg 4 ' Entrada [3:0] $end
$var reg 3 ( S [2:0] $end
$var reg 1 ) clck $end
$var reg 1 * rst $end
$scope module M1 $end
$var wire 3 + S [2:0] $end
$var wire 1 ) clk $end
$var wire 1 $ enable1 $end
$var wire 1 % enable2 $end
$var wire 1 & enable3 $end
$var wire 4 , entrada [3:0] $end
$var wire 1 * reset $end
$var wire 4 - salida [3:0] $end
$var wire 4 . data_bus [3:0] $end
$var wire 4 / aluc [3:0] $end
$var wire 4 0 accu [3:0] $end
$var wire 1 " Zero $end
$var wire 1 # Carry $end
$scope module U1 $end
$var wire 4 1 D [3:0] $end
$var wire 1 $ E $end
$var wire 4 2 Q [3:0] $end
$upscope $end
$scope module U2 $end
$var wire 1 % E $end
$var wire 1 ) clk $end
$var wire 1 * reset $end
$var wire 4 3 q [3:0] $end
$var wire 4 4 d [3:0] $end
$scope module G1 $end
$var wire 1 % E $end
$var wire 1 ) clk $end
$var wire 1 5 d $end
$var wire 1 * reset $end
$var reg 1 6 q $end
$upscope $end
$scope module G2 $end
$var wire 1 % E $end
$var wire 1 ) clk $end
$var wire 1 7 d $end
$var wire 1 * reset $end
$var reg 1 8 q $end
$upscope $end
$scope module G3 $end
$var wire 1 % E $end
$var wire 1 ) clk $end
$var wire 1 9 d $end
$var wire 1 * reset $end
$var reg 1 : q $end
$upscope $end
$scope module G4 $end
$var wire 1 % E $end
$var wire 1 ) clk $end
$var wire 1 ; d $end
$var wire 1 * reset $end
$var reg 1 < q $end
$upscope $end
$upscope $end
$scope module U3 $end
$var wire 4 = A [3:0] $end
$var wire 4 > B [3:0] $end
$var wire 3 ? F [2:0] $end
$var reg 5 @ CR [4:0] $end
$var reg 5 A CS [4:0] $end
$var reg 1 # carry $end
$var reg 4 B salida [3:0] $end
$var reg 1 " zero $end
$upscope $end
$upscope $end
$upscope $end
$enddefinitions $end
#0
$dumpvars
bx B
bx A
bx @
b0 ?
bz >
bx =
x<
x;
x:
x9
x8
x7
x6
x5
bx 4
bx 3
bz 2
b0 1
bx 0
bx /
bz .
bx -
b0 ,
b0 +
0*
0)
b0 (
b0 '
0&
0%
0$
0#
x"
bx !
$end
#1
0;
09
07
05
1"
b0 !
b0 -
b0 /
b0 4
b0 B
06
08
0:
b0 0
b0 3
b0 =
0<
1)
1*
#2
0)
0*
#3
b10 .
b10 2
b10 >
1)
1&
1%
1$
b10 '
b10 ,
b10 1
#4
0)
#5
1)
#6
0)
#7
15
0"
b1 !
b1 -
b1 /
b1 4
b1 B
b1 .
b1 2
b1 >
1)
b10 (
b10 +
b10 ?
b1 '
b1 ,
b1 1
#8
0)
#9
b1 0
b1 3
b1 =
16
1)
#10
0)
#11
17
b11 !
b11 -
b11 /
b11 4
b11 B
b11 .
b11 2
b11 >
1)
b11 '
b11 ,
b11 1
#12
0)
#13
b11 0
b11 3
b11 =
18
1)
#14
0)
#15
19
b111 !
b111 -
b111 /
b111 4
b111 B
b111 A
b100 .
b100 2
b100 >
1)
b11 (
b11 +
b11 ?
b100 '
b100 ,
b100 1
#16
0)
#17
1;
09
b1011 !
b1011 -
b1011 /
b1011 4
b1011 B
b1011 A
b111 0
b111 3
b111 =
1:
1)
#18
0)
#19
19
1<
b1011 0
b1011 3
b1011 =
0:
05
b1110 !
b1110 -
b1110 /
b1110 4
b1110 B
b101 .
b101 2
b101 >
1)
b100 (
b100 +
b100 ?
b101 '
b101 ,
b101 1
#20
0)
#21
09
15
b1011 !
b1011 -
b1011 /
b1011 4
b1011 B
06
b1110 0
b1110 3
b1110 =
1:
1)
#22
0)
#23
0:
b1011 0
b1011 3
b1011 =
16
09
15
b1011 !
b1011 -
b1011 /
b1011 4
b1011 B
b1 @
b1010 .
b1010 2
b1010 >
1)
b1 (
b1 +
b1 ?
b1010 '
b1010 ,
b1010 1
#24
0)
#25
b100 @
b111 .
b111 2
b111 >
1)
b111 '
b111 ,
b111 1
#26
0)
#27
1)
#28
0)
#29
0;
05
b10 !
b10 -
b10 /
b10 4
b10 B
1#
b10010 A
1)
b11 (
b11 +
b11 ?
#30
0)
#31
1;
07
15
b1001 !
b1001 -
b1001 /
b1001 4
b1001 B
0#
b1001 A
0<
b10 0
b10 3
b10 =
06
1)
#32
0)
#33
0;
05
1"
b0 !
b0 -
b0 /
b0 4
b0 B
1#
b10000 A
16
08
b1001 0
b1001 3
b1001 =
1<
1)
#34
0)
#35
19
17
15
0"
b111 !
b111 -
b111 /
b111 4
b111 B
0#
b111 A
0<
b0 0
b0 3
b0 =
06
1)
#36
0)
#37
1;
05
b1110 !
b1110 -
b1110 /
b1110 4
b1110 B
b1110 A
16
18
b111 0
b111 3
b111 =
1:
1)
#38
0)
#39
0;
07
15
b101 !
b101 -
b101 /
b101 4
b101 B
1#
b10101 A
1<
b1110 0
b1110 3
b1110 =
06
1)
