LAB03D/Tabla01POS/Tabla01POS.v
module Tabla01POS();

// Tabla01 POS

  reg A, B, C;
  wire wn1, wn2, wn3, wa1, wa2, wa3, out;


  not n0(wn1, A); 
  not n1(wn2, B);
  not n2(wn3, C);
  or  r0(wa1, A, B, wn3);
  or  r1(wa2, A, wn2, wn3);
  or  r2(wa3, wn1, wn2, C);
  and a1(out, wa1, wa2, wa3);

  initial begin
    $display("A B C | Y");
    $display("-------");
    $monitor("%b %b %b| %b", A, B, C, out);
    A = 0; B = 0; C = 0;
   
    #1 C = 1;
    #1 B = 1; C = 0;
    #1 C = 1;
    #1 A = 1; B = 0; C = 0;
	#1 C = 1;
	#1 B = 1; C = 0;
	#1 C = 1;
    #1 $finish;
  end

  initial 
    begin
      $dumpfile("Tabla01POS_tb.vcd"); 
      $dumpvars(0, Tabla01POS);
    end 

endmodule

LAB03D/Tabla01POS/Tabla01POS_tb.vcd
$date
	Fri Jul 31 21:16:43 2020
$end
$version
	Icarus Verilog
$end
$timescale
	1ps
$end
$scope module Tabla01POS $end
$var wire 1 ! out $end
$var wire 1 " wa1 $end
$var wire 1 # wa2 $end
$var wire 1 $ wa3 $end
$var wire 1 % wn1 $end
$var wire 1 & wn2 $end
$var wire 1 ' wn3 $end
$var reg 1 ( A $end
$var reg 1 ) B $end
$var reg 1 * C $end
$upscope $end
$enddefinitions $end
#0
$dumpvars
0*
0)
0(
1'
1&
1%
1$
1#
1"
1!
$end
#1
0!
0"
0'
1*
#2
1!
1'
1"
0&
0*
1)
#3
0!
0#
0'
1*
#4
1!
1'
1&
1#
0%
0*
0)
1(
#5
0'
1*
#6
0!
0$
1'
0&
0*
1)
#7
1!
1$
0'
1*
