LAB09D/Ejercicio 2/EJ2.v
// Ejercicio 2 Flip Flop tipo D de 1 bit

module FFD1(input clk , input reset, E, input d,  output reg q);

  always@(posedge clk, posedge reset) begin
    if(E == 1) begin
    q <= d;
    end
    if(reset) begin
    q <= 0;
    end
  end
endmodule

// Ejercicio 2 Flip Flop tipo T

module FFT(input clk , input reset, E, input d1, output wire q1);
  wire dn = ~d1;
  FFD1 M1(clk, reset, E, dn, q1);
endmodule

LAB09D/Ejercicio 2/EJ2_tb.v
module testbench();
	reg clk, reset;
	reg D, E;
	wire Q;

	FFT P1(clk, reset, E, D, Q);

	initial begin
	clk = 0; reset = 0; D=0; E=0;
	#1 reset = 1;
  #1 reset = 0; E=1;
  #1 D=1;
  #1 D=0;
  #1 D=1;
  #1 D=0;

	end
	always
    #2 clk = ~clk;
	initial
    #10 $finish;
	initial begin
    $dumpfile("EJ2_tb.vcd");
    $dumpvars(0, testbench);
	end

endmodule

LAB09D/Ejercicio 2/EJ2_tb.vcd
$date
	Sat Oct 31 00:15:38 2020
$end
$version
	Icarus Verilog
$end
$timescale
	1ps
$end
$scope module testbench $end
$var wire 1 ! Q $end
$var reg 1 " D $end
$var reg 1 # E $end
$var reg 1 $ clk $end
$var reg 1 % reset $end
$scope module P1 $end
$var wire 1 # E $end
$var wire 1 $ clk $end
$var wire 1 " d1 $end
$var wire 1 & dn $end
$var wire 1 % reset $end
$var wire 1 ! q1 $end
$scope module M1 $end
$var wire 1 # E $end
$var wire 1 $ clk $end
$var wire 1 & d $end
$var wire 1 % reset $end
$var reg 1 ! q $end
$upscope $end
$upscope $end
$upscope $end
$enddefinitions $end
#0
$dumpvars
1&
0%
0$
0#
0"
x!
$end
#1
0!
1%
#2
1!
1#
0%
1$
#3
0&
1"
#4
1&
0"
0$
#5
0&
1"
#6
0!
1&
0"
1$
#8
0$
#10
1!
1$
