LAB03D/Tabla03POS/Tabla03POS.v
module Tabla03POS();

// Tabla03 POS

  reg A, B, C, D;
  wire wn1, wn2, wn3, wn4, wa1, wa2, wa3, wa4, wa5, wa6, wa7, wa8, wa9, out;


  not n0(wn1, A); 
  not n1(wn2, B);
  not n2(wn3, C);
  not n3(wn4, D);
  or  r0(wa1, A, wn2, C, D);
  or  r1(wa2, A, wn2, C, wn4);
  or  r2(wa3, A, wn2, wn3, D);
  or  r3(wa4, A, wn2, wn3, wn4);
  or  r4(wa5, wn1, B, C, wn4);
  or  r5(wa6, wn1, B, wn3, wn4);
  or  r6(wa7, wn1, wn2, C, D);
  or  r7(wa8, wn1, wn2, C, wn4);
  or  r8(wa9, wn1, wn2, wn3, wn4);
  and a1(out, wa1, wa2, wa3, wa4, wa5, wa6, wa7, wa8, wa9);

  initial begin
    $display("A B C D | Y");
    $display("-------");
    $monitor("%b %b %b %b| %b", A, B, C, D, out);
   A = 0; B = 0; C = 0; D = 0;
   
    #1 D = 1;
    #1 C = 1; D = 0;
    #1 D = 1;
    #1 B = 1; C = 0; D = 0;
	#1 D = 1;
	#1 C = 1; D = 0;
	#1 D = 1;
	#1 A = 1; B = 0; C = 0; D = 0;
	#1 D = 1;
    #1 C = 1; D = 0;
    #1 D = 1;
    #1 B = 1; C = 0; D = 0;
	#1 D = 1;
	#1 C = 1; D = 0;
	#1 D = 1;
    #1 $finish;
  end

  initial 
    begin
      $dumpfile("Tabla03POS_tb.vcd"); 
      $dumpvars(0, Tabla03POS);
    end 

endmodule

LAB03D/Tabla03POS/Tabla03POS_tb.vcd
$date
	Fri Jul 31 18:36:25 2020
$end
$version
	Icarus Verilog
$end
$timescale
	1ps
$end
$scope module Tabla03POS $end
$var wire 1 ! out $end
$var wire 1 " wa1 $end
$var wire 1 # wa2 $end
$var wire 1 $ wa3 $end
$var wire 1 % wa4 $end
$var wire 1 & wa5 $end
$var wire 1 ' wa6 $end
$var wire 1 ( wa7 $end
$var wire 1 ) wa8 $end
$var wire 1 * wa9 $end
$var wire 1 + wn1 $end
$var wire 1 , wn2 $end
$var wire 1 - wn3 $end
$var wire 1 . wn4 $end
$var reg 1 / A $end
$var reg 1 0 B $end
$var reg 1 1 C $end
$var reg 1 2 D $end
$upscope $end
$enddefinitions $end
#0
$dumpvars
02
01
00
0/
1.
1-
1,
1+
1*
1)
1(
1'
1&
1%
1$
1#
1"
1!
$end
#1
0.
12
#2
1.
0-
02
11
#3
0.
12
#4
0!
1.
1#
0"
1-
0,
02
01
10
#5
0#
1"
0.
12
#6
0$
1.
1#
0-
02
11
#7
0%
1$
0.
12
#8
1!
1.
1-
1'
1&
1,
1%
0+
02
01
00
1/
#9
0!
0&
0.
12
#10
1!
1.
1&
0-
02
11
#11
0!
0'
0.
12
#12
1.
1)
0(
1-
1'
0,
02
01
10
#13
0)
1(
0.
12
#14
1!
1.
1)
0-
02
11
#15
0!
0*
0.
12
